llama_index/storage/index_store/asimov/_version.py
llama_index_storage_index_store_asimov-0.0.1.dist-info/METADATA
llama_index_storage_index_store_asimov-0.0.1.dist-info/WHEEL
llama_index_storage_index_store_asimov-0.0.1.dist-info/RECORD
