Metadata-Version: 2.4
Name: llama-index-storage-index-store-asimov
Version: 0.0.1
Summary: llama-index index_store ASIMOV integration
Project-URL: Homepage, https://github.com/asimov-platform
Project-URL: Repository, https://github.com/asimov-platform/llama-index-asimov
Project-URL: Changelog, https://github.com/asimov-platform/llama-index-asimov/blob/master/CHANGES.md
Project-URL: Releases, https://github.com/asimov-platform/llama-index-asimov/releases
Project-URL: Issues, https://github.com/asimov-platform/llama-index-asimov/issues
Author-email: ASIMOV Protocol <support@asimov.so>
License-Expression: Unlicense
Requires-Python: >=3.9
